{
  "scan_timestamp": "2026-01-20 09:34:26",
  "matches_found": 8,
  "data": [
    {
      "symbol": "SLB",
      "price": 46.73,
      "rsi": 84.28,
      "stoch_k": 90.4,
      "extension": "+20.2%",
      "volume": 17373076,
      "score": 5,
      "bonus_factors": [
        "Stoch Hook Down",
        "Extreme RSI (84)",
        "Parabolic (+20% vs SMA)"
      ]
    },
    {
      "symbol": "ROST",
      "price": 192.36,
      "rsi": 76.19,
      "stoch_k": 88.64,
      "extension": "+8.5%",
      "volume": 3269731,
      "score": 3,
      "bonus_factors": [
        "Stoch Hook Down",
        "Extreme RSI (76)"
      ]
    },
    {
      "symbol": "MU",
      "price": 362.75,
      "rsi": 74.34,
      "stoch_k": 84.08,
      "extension": "+36.4%",
      "volume": 47901925,
      "score": 3,
      "bonus_factors": [
        "Parabolic (+20% vs SMA)",
        "Bearish RSI Divergence"
      ]
    },
    {
      "symbol": "LRCX",
      "price": 222.96,
      "rsi": 73.91,
      "stoch_k": 80.52,
      "extension": "+30.2%",
      "volume": 14392666,
      "score": 3,
      "bonus_factors": [
        "Parabolic (+20% vs SMA)",
        "Bearish RSI Divergence"
      ]
    },
    {
      "symbol": "SBUX",
      "price": 92.99,
      "rsi": 72.95,
      "stoch_k": 92.36,
      "extension": "+8.3%",
      "volume": 8958234,
      "score": 2,
      "bonus_factors": [
        "Stoch Hook Down"
      ]
    },
    {
      "symbol": "HAL",
      "price": 32.57,
      "rsi": 71.85,
      "stoch_k": 84.25,
      "extension": "+14.9%",
      "volume": 10404904,
      "score": 2,
      "bonus_factors": [
        "Stoch Hook Down"
      ]
    },
    {
      "symbol": "XOM",
      "price": 129.89,
      "rsi": 68.51,
      "stoch_k": 85.27,
      "extension": "+9.1%",
      "volume": 16592354,
      "score": 2,
      "bonus_factors": [
        "Stoch Hook Down"
      ]
    },
    {
      "symbol": "RTX",
      "price": 201.92,
      "rsi": 78.27,
      "stoch_k": 98.64,
      "extension": "+12.2%",
      "volume": 4825922,
      "score": 1,
      "bonus_factors": [
        "Extreme RSI (78)"
      ]
    }
  ]
}