{
  "lastUpdated": "2026-02-09T19:20:52.282274",
  "stocks": [
    {
      "ticker": "RELX",
      "company_name": "Relx PLC ADR",
      "earnings_date": "2026-02-12",
      "ai_decision": {
        "decision": "Good Idea",
        "confidence_score": 9,
        "runup_percentage": 4.0,
        "rationale": "Extremely oversold RSI and a recent 'Buy' upgrade suggest strong potential for a pre-earnings bounce before the imminent February 12th results."
      }
    },
    {
      "ticker": "VRSK",
      "company_name": "Verisk Analytics Inc",
      "earnings_date": "2026-02-18",
      "ai_decision": {
        "decision": "Good Idea",
        "confidence_score": 8,
        "runup_percentage": 3.5,
        "rationale": "Deeply oversold RSI combined with a significant target price and general market bullishness suggests a strong pre-earnings recovery."
      }
    },
    {
      "ticker": "BKNG",
      "company_name": "Booking Holdings Inc",
      "earnings_date": "2026-02-18",
      "ai_decision": {
        "decision": "Bad Idea",
        "confidence_score": 6,
        "runup_percentage": 0.0,
        "rationale": "Despite being oversold, recent news explicitly notes a 4% slide linked to upcoming earnings, suggesting negative sentiment or headwinds that could negate a pre-earnings bounce."
      }
    },
    {
      "ticker": "MCO",
      "company_name": "Moodys Corporation",
      "earnings_date": "2026-02-18",
      "ai_decision": {
        "decision": "Bad Idea",
        "confidence_score": 6,
        "runup_percentage": 0.0,
        "rationale": "While oversold, a recent Goldman Sachs price target reduction, despite overall analyst interest, introduces caution and mixed sentiment that could prevent a pre-earnings run."
      }
    },
    {
      "ticker": "SPOT",
      "company_name": "Spotify Technology SA",
      "earnings_date": "2026-02-10",
      "ai_decision": {
        "decision": "Good Idea",
        "confidence_score": 7,
        "runup_percentage": 3.0,
        "rationale": "Despite a recent price target cut, Spotify's deeply oversold RSI, significant target upside, and recent positive news regarding new features and partnerships heading into Q4 earnings create a strong pre-earnings run-up potential."
      }
    },
    {
      "ticker": "SPGI",
      "company_name": "S&P Global Inc",
      "earnings_date": "2026-02-10",
      "ai_decision": {
        "decision": "Good Idea",
        "confidence_score": 7,
        "runup_percentage": 2.5,
        "rationale": "An oversold RSI and substantial target price upside suggest a pre-earnings bounce, despite the lack of strong direct bullish news for the company."
      }
    },
    {
      "ticker": "FIS",
      "company_name": "Fidelity National Information Services Inc",
      "earnings_date": "2026-02-10",
      "ai_decision": {
        "decision": "Good Idea",
        "confidence_score": 7,
        "runup_percentage": 2.5,
        "rationale": "The stock is significantly oversold with a high target price, indicating potential for a pre-earnings run-up despite a lack of direct bullish news."
      }
    },
    {
      "ticker": "HUM",
      "company_name": "Humana Inc",
      "earnings_date": "2026-02-11",
      "ai_decision": {
        "decision": "Good Idea",
        "confidence_score": 8,
        "runup_percentage": 3.5,
        "rationale": "The stock is oversold with substantial target upside, and a recent positive news catalyst (AI partnership with Google Cloud) bodes well for a pre-earnings run."
      }
    },
    {
      "ticker": "WAT",
      "company_name": "Waters Corporation",
      "earnings_date": "2026-02-12",
      "ai_decision": {
        "decision": "Bad Idea",
        "confidence_score": 10,
        "runup_percentage": 0.0,
        "rationale": "The news clearly indicates the company has already reported earnings with a 'low profit outlook,' leading to a post-earnings decline, making a pre-earnings run-up trade impossible."
      }
    },
    {
      "ticker": "FIG",
      "company_name": "Figma, Inc.",
      "earnings_date": "2026-02-18",
      "ai_decision": {
        "decision": "Bad Idea",
        "confidence_score": 9,
        "runup_percentage": 0.0,
        "rationale": "Despite being oversold with significant target upside, the CFO's recent stock sale is a strong bearish signal that outweighs potential pre-earnings optimism."
      }
    },
    {
      "ticker": "PODD",
      "company_name": "Insulet Corporation",
      "earnings_date": "2026-02-18",
      "ai_decision": {
        "decision": "Good Idea",
        "confidence_score": 9,
        "runup_percentage": 4.0,
        "rationale": "The stock is oversold with substantial target upside, strongly supported by recent bullish news of a key product launch and international expansion, making a pre-earnings run highly probable."
      }
    },
    {
      "ticker": "ALNY",
      "company_name": "Alnylam Pharmaceuticals Inc",
      "earnings_date": "2026-02-12",
      "ai_decision": {
        "decision": "Good Idea",
        "confidence_score": 9,
        "runup_percentage": 4.0,
        "rationale": "Deeply oversold RSI, significant target upside, and consistent bullish news highlighting expected earnings growth position this stock for a strong pre-earnings rally."
      }
    },
    {
      "ticker": "DASH",
      "company_name": "DoorDash, Inc. Class A Common Stock",
      "earnings_date": "2026-02-18",
      "ai_decision": {
        "decision": "Bad Idea",
        "confidence_score": 8,
        "runup_percentage": 0.0,
        "rationale": "Despite being oversold, recent repeated news of a somewhat-bearish legal settlement in Chicago creates significant negative sentiment likely to hinder any pre-earnings run-up."
      }
    },
    {
      "ticker": "EW",
      "company_name": "Edwards Lifesciences Corp",
      "earnings_date": "2026-02-10",
      "ai_decision": {
        "decision": "Good Idea",
        "confidence_score": 6,
        "runup_percentage": 2.0,
        "rationale": "An oversold RSI and a decent target price suggest some potential for a pre-earnings bounce, though a lack of strong direct bullish catalysts tempers the outlook."
      }
    },
    {
      "ticker": "COIN",
      "company_name": "Coinbase Global Inc",
      "earnings_date": "2026-02-12",
      "ai_decision": {
        "decision": "Bad Idea",
        "confidence_score": 5,
        "runup_percentage": 0.0,
        "rationale": "Despite being oversold with substantial target upside, the lack of direct, relevant news or specific catalysts for Coinbase, coupled with its inherent volatility, makes a predictable pre-earnings run-up highly speculative."
      }
    }
  ]
}